GraphiteEncoder-0.1.4.dist-info/METADATA
GraphiteEncoder-0.1.4.dist-info/RECORD
GraphiteEncoder-0.1.4.dist-info/WHEEL
GraphiteEncoder-0.1.4.dist-info/top_level.txt
graphite_encoder/GraphiteEncoder.py
graphite_encoder/__init__.py
tests/__init__.py
tests/test_encoder.py
