Metadata-Version: 2.1
Name: GraphiteEncoder
Version: 0.1.4
Summary: UNKNOWN
Home-page: UNKNOWN
Author: Yun Xu
Author-email: yunx@zillowgroup.com
License: UNKNOWN
Platform: UNKNOWN
Classifier: Development Status :: 3 - Alpha
Classifier: Operating System :: MacOS
Classifier: Operating System :: POSIX :: Linux
Classifier: Topic :: System :: Software Distribution
Classifier: License :: OSI Approved :: MIT License
Classifier: Programming Language :: Python
Classifier: Programming Language :: Python :: 2
Classifier: Programming Language :: Python :: 2.7
